enveloc/__init__.py
enveloc/core.py
enveloc/default_vel_model.tvel
enveloc/example_utils.py
enveloc/plotting_utils.py
enveloc/xcorr_utils.py
enveloc/xloc_utils.py
enveloc-1.1.5.dist-info/licenses/LICENSE
enveloc-1.1.5.dist-info/METADATA
enveloc-1.1.5.dist-info/WHEEL
enveloc-1.1.5.dist-info/top_level.txt
enveloc-1.1.5.dist-info/RECORD
