Metadata-Version: 2.4
Name: enveloc
Version: 1.1.5
Summary: enveloc - envelope cross-correlation location method
Home-page: https://github.com/awech/enveloc
Download-URL: https://github.com/awech/enveloc/archive/v1.1.5.tar.gz
Author: Aaron Wech
Author-email: awech@usgs.gov
Classifier: Programming Language :: Python :: 3.11
Classifier: License :: OSI Approved :: GNU General Public License v3 (GPLv3)
Classifier: Operating System :: OS Independent
Classifier: Development Status :: 4 - Beta
Classifier: Intended Audience :: Science/Research
Classifier: Topic :: Scientific/Engineering
Requires-Python: >=3.8
License-File: LICENSE
Requires-Dist: cython
Requires-Dist: obspy
Requires-Dist: cartopy
Requires-Dist: scikit-learn
Requires-Dist: utm
Dynamic: download-url
Dynamic: license-file
